pykol/__init__.py
pykol/connection.py
skydata_pykol-0.0.9.dist-info/METADATA
skydata_pykol-0.0.9.dist-info/WHEEL
skydata_pykol-0.0.9.dist-info/top_level.txt
skydata_pykol-0.0.9.dist-info/zip-safe
skydata_pykol-0.0.9.dist-info/RECORD
