Metadata-Version: 2.1
Name: skydata_pykol
Version: 0.0.9
Summary: A Python driver for Kol.
Home-page: https://gitlab.com/skydata.app/pykol
Author: Kyle Kloberdanz
Author-email: kyle.g.kloberdanz@gmail.com
Classifier: Programming Language :: Python :: 3
Classifier: License :: OSI Approved :: MIT License
Classifier: Operating System :: OS Independent
Requires-Python: >=3.6
